{
    "sensorId": 1,
    "loggedAt": "2026-01-09T15:49:01.233189Z",
    "gatewayId": 1,
    "lat": 36.424343,
    "lng": 127.418694,
    "temp": "8.31",
    "objectTemp": "8.13",
    "humi": "44.17",
    "pressure": "1012.09",
    "dewPoint": "0.00",
    "surface": 1,
    "skid": 0,
    "heuristicsSkid": -1,
    "kmaWeather": -1,
    "futureTemp": null,
    "surfaceStatus": null,
    "distance in mm": "819.04",
    "gps": {
        "lat": 36.424343,
        "lng": 127.418694,
        "alt": null,
        "speed": 0.03,
        "gqi": 0,
        "hdop": 99.99
    },
    "surfaceType": {
        "result": 1
    },
    "version": 3.2
}