{
    "sensorId": 1,
    "loggedAt": "2026-02-06T16:29:20.483867Z",
    "gatewayId": 1,
    "lat": 36.368784,
    "lng": 127.404224,
    "temp": "8.00",
    "objectTemp": "8.33",
    "humi": "39.66",
    "pressure": "1017.67",
    "dewPoint": "0.00",
    "surface": 1,
    "skid": 0,
    "heuristicsSkid": -1,
    "kmaWeather": -1,
    "futureTemp": null,
    "surfaceStatus": null,
    "distance in mm": "913.89",
    "gps": {
        "lat": 36.368784,
        "lng": 127.404224,
        "alt": null,
        "speed": 14.68,
        "gqi": 0,
        "hdop": 99.99
    },
    "surfaceType": {
        "result": 1
    },
    "version": 3.2
}