{
    "sensorId": 1,
    "loggedAt": "2026-01-09T16:06:15.716662Z",
    "gatewayId": 1,
    "lat": 36.36328,
    "lng": 127.366263,
    "temp": "7.87",
    "objectTemp": "5.93",
    "humi": "45.93",
    "pressure": "1014.30",
    "dewPoint": "0.00",
    "surface": 1,
    "skid": 0,
    "heuristicsSkid": -1,
    "kmaWeather": -1,
    "futureTemp": null,
    "surfaceStatus": null,
    "distance in mm": "832.73",
    "gps": {
        "lat": 36.36328,
        "lng": 127.366263,
        "alt": null,
        "speed": 45.8,
        "gqi": 0,
        "hdop": 99.99
    },
    "surfaceType": {
        "result": 1
    },
    "version": 3.2
}